{
  "generated_at": "2026-03-19T19:27:17.451116",
  "methodology": {
    "risk_free_rate": 0.065,
    "transaction_cost": 0.0005,
    "slippage": 0.0002,
    "position_sizing": "regime-aware fractional Kelly",
    "validation": "expanding window walk-forward"
  },
  "val": {
    "split": "val",
    "n_days": 177,
    "n_trades": 60,
    "total_return_pct": -8.38,
    "annual_return_pct": -11.72,
    "sharpe": -3.9,
    "sortino": -5.912,
    "calmar": -1.473,
    "omega": 0.503,
    "profit_factor": 0.637,
    "max_drawdown": -0.0795,
    "max_dd_pct": -7.95,
    "avg_drawdown": -0.0333,
    "max_dd_duration_days": 176,
    "var_95": -0.005,
    "cvar_95": -0.0069,
    "var_95_pct": -0.5,
    "cvar_95_pct": -0.69,
    "win_rate": 0.4294,
    "avg_win": 0.002,
    "avg_loss": -0.0025,
    "expectancy": -0.0006,
    "payoff_ratio": 0.796,
    "alpha_annual": -0.1212,
    "alpha_pct": -12.12,
    "beta": -0.0117,
    "r_squared": 0.0007,
    "information_ratio": -2.67,
    "strategy_ann_return": -11.72,
    "benchmark_ann_return": 20.05,
    "monte_carlo": {
      "sharpe_mean": -4.011,
      "sharpe_std": 1.315,
      "sharpe_ci_low": -6.684,
      "sharpe_ci_high": -1.505,
      "prob_positive_sharpe": 0.001
    }
  },
  "test": {
    "split": "test",
    "n_days": 355,
    "n_trades": 159,
    "total_return_pct": -8.62,
    "annual_return_pct": -6.2,
    "sharpe": -2.254,
    "sortino": -3.13,
    "calmar": -0.68,
    "omega": 0.644,
    "profit_factor": 0.805,
    "max_drawdown": -0.0912,
    "max_dd_pct": -9.12,
    "avg_drawdown": -0.0398,
    "max_dd_duration_days": 353,
    "var_95": -0.0056,
    "cvar_95": -0.0082,
    "var_95_pct": -0.56,
    "cvar_95_pct": -0.82,
    "win_rate": 0.4704,
    "avg_win": 0.0022,
    "avg_loss": -0.0024,
    "expectancy": -0.0002,
    "payoff_ratio": 0.906,
    "alpha_annual": -0.0654,
    "alpha_pct": -6.54,
    "beta": 0.0464,
    "r_squared": 0.01,
    "information_ratio": -0.985,
    "strategy_ann_return": -6.2,
    "benchmark_ann_return": 5.91,
    "monte_carlo": {
      "sharpe_mean": -2.272,
      "sharpe_std": 0.885,
      "sharpe_ci_low": -4.068,
      "sharpe_ci_high": -0.56,
      "prob_positive_sharpe": 0.004
    }
  },
  "walk_forward_windows": [
    {
      "window": 1,
      "train_days": 70,
      "test_days": 21,
      "test_start": "70",
      "test_end": "90",
      "sharpe": -5.305,
      "sortino": -9.971,
      "total_return": -0.27,
      "bh_return": -1.95,
      "alpha": 1.68,
      "win_rate": 0.524,
      "max_drawdown": -0.6
    },
    {
      "window": 2,
      "train_days": 91,
      "test_days": 21,
      "test_start": "91",
      "test_end": "111",
      "sharpe": -5.079,
      "sortino": -5.067,
      "total_return": -1.16,
      "bh_return": 7.73,
      "alpha": -8.88,
      "win_rate": 0.429,
      "max_drawdown": -1.7
    },
    {
      "window": 3,
      "train_days": 112,
      "test_days": 21,
      "test_start": "112",
      "test_end": "132",
      "sharpe": -7.01,
      "sortino": -9.153,
      "total_return": -1.96,
      "bh_return": 4.63,
      "alpha": -6.59,
      "win_rate": 0.381,
      "max_drawdown": -2.26
    },
    {
      "window": 4,
      "train_days": 133,
      "test_days": 21,
      "test_start": "133",
      "test_end": "153",
      "sharpe": -2.566,
      "sortino": -4.754,
      "total_return": -1.1,
      "bh_return": -0.25,
      "alpha": -0.85,
      "win_rate": 0.381,
      "max_drawdown": -2.3
    },
    {
      "window": 5,
      "train_days": 154,
      "test_days": 21,
      "test_start": "154",
      "test_end": "174",
      "sharpe": -5.567,
      "sortino": -7.806,
      "total_return": -1.14,
      "bh_return": 0.84,
      "alpha": -1.98,
      "win_rate": 0.333,
      "max_drawdown": -1.5
    }
  ],
  "walk_forward_summary": {
    "n_windows": 5,
    "sharpe_mean": -5.105,
    "sharpe_std": 1.437,
    "alpha_mean_pct": -3.32,
    "positive_windows": 1
  }
}